django_hashed_bundle/__init__.py
django_hashed_bundle/apps.py
django_hashed_bundle/tests.py
django_hashed_bundle/migrations/__init__.py
django_hashed_bundle/templatetags/__init__.py
django_hashed_bundle/templatetags/hashed_bundle.py
django_hashed_bundle-0.1.dist-info/LICENSE
django_hashed_bundle-0.1.dist-info/METADATA
django_hashed_bundle-0.1.dist-info/WHEEL
django_hashed_bundle-0.1.dist-info/top_level.txt
django_hashed_bundle-0.1.dist-info/RECORD
